janus.py
setup.py
libjanus.egg-info/PKG-INFO
libjanus.egg-info/SOURCES.txt
libjanus.egg-info/dependency_links.txt
libjanus.egg-info/top_level.txt