Metadata-Version: 1.1
Name: libjanus
Version: 1.0.1
Summary: A minimalist argument-parsing library.
Home-page: https://github.com/dmulholland/janus
Author: Darren Mulholland
Author-email: UNKNOWN
License: Public Domain
Platform: UNKNOWN
Classifier: Programming Language :: Python :: 3
Classifier: Operating System :: OS Independent
Classifier: License :: Public Domain
